satcomsim/__init__.py
satcomsim/models/__init__.py
satcomsim/models/orbit.py
satcomsim/models/planet.py
satcomsim/models/point.py
satcomsim/models/point_cart.py
satcomsim/models/point_pol.py
satcomsim/models/propulsion.py
satcomsim/models/satellite.py
satcomsim/simulation/__init__.py
satcomsim/simulation/simulation.py
satcomsim/utils/__init__.py
satcomsim/utils/config_manager.py
satcomsim/utils/constants.py
satcomsim/utils/tle_importer.py
satcomsim-0.1.1.dist-info/LICENSE
satcomsim-0.1.1.dist-info/METADATA
satcomsim-0.1.1.dist-info/WHEEL
satcomsim-0.1.1.dist-info/RECORD
