Metadata-Version: 2.3
Name: satcomsim
Version: 0.1.1
Summary: 
License: Apache License
Author: Ihor Savenko
Author-email: csigorek@gmail.com
Requires-Python: >=3.10
Classifier: License :: Other/Proprietary License
Classifier: Programming Language :: Python :: 3
Classifier: Programming Language :: Python :: 3.10
Classifier: Programming Language :: Python :: 3.11
Classifier: Programming Language :: Python :: 3.12
Classifier: Programming Language :: Python :: 3.13
Requires-Dist: annotated-types (==0.7.0)
Requires-Dist: anyio (==4.9.0)
Requires-Dist: certifi (==2025.4.26)
Requires-Dist: charset-normalizer (==3.4.2)
Requires-Dist: click (==8.2.0)
Requires-Dist: colorama (==0.4.6)
Requires-Dist: contourpy (==1.3.2)
Requires-Dist: cycler (==0.12.1)
Requires-Dist: fonttools (==4.58.0)
Requires-Dist: h11 (==0.16.0)
Requires-Dist: idna (==3.10)
Requires-Dist: jplephem (==2.22)
Requires-Dist: kiwisolver (==1.4.8)
Requires-Dist: matplotlib (==3.10.3)
Requires-Dist: msgpack (==1.1.0)
Requires-Dist: numpy (==2.2.5)
Requires-Dist: packaging (==25.0)
Requires-Dist: pillow (==11.2.1)
Requires-Dist: pydantic (==2.11.4)
Requires-Dist: pydantic_core (==2.33.2)
Requires-Dist: python-dateutil (==2.9.0.post0)
Requires-Dist: requests (==2.32.3)
Requires-Dist: scipy (==1.15.3)
Requires-Dist: sgp4 (==2.24)
Requires-Dist: six (==1.17.0)
Requires-Dist: skyfield (==1.53)
Requires-Dist: sniffio (==1.3.1)
Requires-Dist: starlette (==0.46.2)
Requires-Dist: typing-inspection (==0.4.0)
Requires-Dist: typing_extensions (==4.13.2)
Requires-Dist: urllib3 (==2.4.0)
Project-URL: Homepage, https://github.com/veylor-hq/satcomsim
